huaweicloudsdkdsc/__init__.py
huaweicloudsdkdsc/v1/__init__.py
huaweicloudsdkdsc/v1/dsc_async_client.py
huaweicloudsdkdsc/v1/dsc_client.py
huaweicloudsdkdsc/v1/model/__init__.py
huaweicloudsdkdsc/v1/model/add_buckets_request.py
huaweicloudsdkdsc/v1/model/add_buckets_response.py
huaweicloudsdkdsc/v1/model/add_rule_group_request.py
huaweicloudsdkdsc/v1/model/add_rule_group_response.py
huaweicloudsdkdsc/v1/model/add_rule_request.py
huaweicloudsdkdsc/v1/model/add_rule_response.py
huaweicloudsdkdsc/v1/model/add_scan_job_request.py
huaweicloudsdkdsc/v1/model/add_scan_job_response.py
huaweicloudsdkdsc/v1/model/asset_name_request.py
huaweicloudsdkdsc/v1/model/batch_add_data_mask_request.py
huaweicloudsdkdsc/v1/model/batch_add_data_mask_response.py
huaweicloudsdkdsc/v1/model/bucket.py
huaweicloudsdkdsc/v1/model/bucket_bean.py
huaweicloudsdkdsc/v1/model/buckets_request.py
huaweicloudsdkdsc/v1/model/change_db_template_operation_request.py
huaweicloudsdkdsc/v1/model/change_db_template_operation_response.py
huaweicloudsdkdsc/v1/model/change_rule_request.py
huaweicloudsdkdsc/v1/model/change_rule_response.py
huaweicloudsdkdsc/v1/model/columns.py
huaweicloudsdkdsc/v1/model/create_database_water_mark_request.py
huaweicloudsdkdsc/v1/model/create_database_water_mark_response.py
huaweicloudsdkdsc/v1/model/create_doc_watermark_by_address_request.py
huaweicloudsdkdsc/v1/model/create_doc_watermark_by_address_request_body.py
huaweicloudsdkdsc/v1/model/create_doc_watermark_by_address_response.py
huaweicloudsdkdsc/v1/model/create_doc_watermark_request.py
huaweicloudsdkdsc/v1/model/create_doc_watermark_request_body.py
huaweicloudsdkdsc/v1/model/create_doc_watermark_response.py
huaweicloudsdkdsc/v1/model/create_image_watermark_by_address_request.py
huaweicloudsdkdsc/v1/model/create_image_watermark_by_address_request_body.py
huaweicloudsdkdsc/v1/model/create_image_watermark_by_address_response.py
huaweicloudsdkdsc/v1/model/create_image_watermark_request.py
huaweicloudsdkdsc-3.1.184.dist-info/METADATA
huaweicloudsdkdsc-3.1.184.dist-info/WHEEL
huaweicloudsdkdsc-3.1.184.dist-info/licenses/LICENSE
huaweicloudsdkdsc-3.1.184.dist-info/RECORD
